[
    {
        "nume": "DELEU",
        "email": "mihaela8380@gmail.com",
        "mesaj": "dfsfsdf",
        "data": "2025-03-26 09:13:40"
    },
    {
        "nume": "DELEU",
        "email": "mihaela8380@gmail.com",
        "mesaj": "dfsfsdf",
        "data": "2025-03-26 09:14:08"
    },
    {
        "nume": "DELEU",
        "email": "mihaela8380@gmail.com",
        "mesaj": "dfsfsdf",
        "data": "2025-03-26 09:14:09"
    },
    {
        "nume": "DELEU",
        "email": "mihaela8380@gmail.com",
        "mesaj": "dfsfsdf",
        "data": "2025-03-26 09:14:17"
    },
    {
        "nume": "DELEU",
        "email": "mihaela8380@gmail.com",
        "mesaj": "dfsfsdf",
        "data": "2025-03-26 09:14:22"
    },
    {
        "nume": "DELEU",
        "email": "mihaela8380@gmail.com",
        "mesaj": "dfsfsdf",
        "data": "2025-03-26 11:42:44"
    },
    {
        "nume": "DELEU",
        "email": "mihaela8380@gmail.com",
        "mesaj": "dfsfsdf",
        "data": "2025-03-26 11:42:45"
    },
    {
        "nume": "fvhbjnkm",
        "email": "mihaela8380@gmail.com",
        "mesaj": "cdgfhgjk",
        "data": "2025-03-26 11:43:15"
    },
    {
        "nume": "fvhbjnkm",
        "email": "mihaela8380@gmail.com",
        "mesaj": "cdgfhgjk",
        "data": "2025-03-26 11:43:18"
    }
]